<?xml version="1.0" encoding="UTF-8"?>
<!DOCTYPE struts PUBLIC
        "-//Apache Software Foundation//DTD Struts Configuration 2.0//EN"
        "http://struts.apache.org/dtds/struts-2.0.dtd">
<struts>
	<package name="rlgl020442" extends="rlgl" namespace="/">
	    <action name="rlgl020442Init"
			class="com.rlglsys.action.continumedicaleducation.projectstraining.Rlgl020442InitAction" method="execute">
			<result name="success">/WEB-INF/jsp/rlgl020442.jsp</result>
		</action>
		
		<action name="rlgl020442Search"
			class="com.rlglsys.action.continumedicaleducation.projectstraining.Rlgl020442SearchAction" method="execute">
			<result name="success">/WEB-INF/jsp/rlgl020442.jsp</result>
		</action>
		
		<action name="rlgl020442Redirect"
			class="com.rlglsys.action.continumedicaleducation.projectstraining.Rlgl020442RedirectAction" method="execute">
			<result name="success" type="redirectAction">
				<param name="actionName">rlgl020430Init</param>
			</result>
		</action>
		
		<action name="rlgl020442GrantCredit"
			class="com.rlglsys.action.continumedicaleducation.projectstraining.Rlgl020442GrantCreditAction" method="execute">
			<result name="success" type="redirectAction">
				<param name="actionName">rlgl020442Redirect</param>
			</result>
		</action>
	</package>
</struts>

