<?xml version="1.0" encoding="UTF-8"?>
<!DOCTYPE struts PUBLIC
        "-//Apache Software Foundation//DTD Struts Configuration 2.0//EN"
        "http://struts.apache.org/dtds/struts-2.0.dtd">
<struts>
	<package name="rlgl010307" extends="rlgl" namespace="/">
	   <action name="rlgl010307Init" class="com.rlglsys.action.hiringmanage.personmanage.Rlgl010307InitAction"
            method="execute">
            <result name="success">/WEB-INF/jsp/rlgl010307.jsp</result>
        </action>
       <action name="rlgl010307Search" class="com.rlglsys.action.hiringmanage.personmanage.Rlgl010307SearchAction"
            method="execute">
            <result name="success">/WEB-INF/jsp/rlgl010307.jsp</result>
        </action>
        <action name="rlgl010307Delete" class="com.rlglsys.action.hiringmanage.personmanage.Rlgl010307DeleteAction"
            method="execute">
            <result name="success">/WEB-INF/jsp/rlgl010307.jsp</result>
        </action>
	</package>
</struts>

