<?xml version="1.0" encoding="UTF-8"?>
<!DOCTYPE struts PUBLIC
        "-//Apache Software Foundation//DTD Struts Configuration 2.0//EN"
        "http://struts.apache.org/dtds/struts-2.0.dtd">
<struts>
    <package name="rlgl020909" extends="rlgl" namespace="/">
       <!-- 初期化处理 -->
       <action name="rlgl020909Init"
        class="com.rlglsys.action.continumedicaleducation.statisticalanalysis.Rlgl020909InitAction"
            method="execute">
            <result name="success">/WEB-INF/jsp/rlgl020909.jsp</result>
       </action>
       <!-- 查询处理 -->
       <action name="rlgl020909Search"
        class="com.rlglsys.action.continumedicaleducation.statisticalanalysis.Rlgl020909SearchAction" method="execute">
            <result name="success">/WEB-INF/jsp/rlgl020909.jsp</result>
       </action>
    </package>
</struts>

